ddragon/__init__.py
ddragon/mirror.py
ddragon-0.1.1.dist-info/METADATA
ddragon-0.1.1.dist-info/WHEEL
ddragon-0.1.1.dist-info/top_level.txt
ddragon-0.1.1.dist-info/RECORD
