Metadata-Version: 2.1
Name: ddragon
Version: 0.1.1
Summary: Host your own ddragon mirror for League of Legends static data and images, relying on dragontail
Home-page: https://github.com/Canisback/ddragon
Author: Canisback
Author-email: canisback@gmail.com
License: UNKNOWN
Keywords: python,ddragon
Platform: UNKNOWN
Requires-Dist: requests
Provides-Extra: image_resize
Requires-Dist: pillow ; extra == 'image_resize'
Requires-Dist: python-resize-image ; extra == 'image_resize'
